{
    "output_directory":"../2014/",
    "output_file":"20141104__nj__temp.csv",
    "us_house":{
        "input_directory":"../../openelections-sources-nj/2014/special_11042014/csv/",
        "input_files": [
                {
                    "office":"U.S. House",
                    "file":"tabula-2014-special-us-hor-gen-elec-results-by-district-district-01-burlington.csv",
                    "county":"Burlington",
                    "district":"1",
                    "columns":"*"
                },
                {
                    "office":"U.S. House",
                    "file":"tabula-2014-special-us-hor-gen-elec-results-by-district-district-01-camden.csv",
                    "county":"Camden",
                    "district":"1",
                    "columns":"*"
                },
                {
                    "office":"U.S. House",
                    "file":"tabula-2014-special-us-hor-gen-elec-results-by-district-district-01-gloucester.csv",
                    "county":"Gloucester",
                    "district":"1",
                    "columns":"*"
                }
            ]
        }
}
